{"title":"The.Colbert.Report.2009.11.03.Andrew.Sullivan.PDTV.XviD-CHGRP.[V","uid":5148059,"size":183164928,"categoryP":"video","categoryS":"tv_shows","magnet":"?xt=urn:btih:1017591f4b37e627dbf12c1ffc8f2fc22454d66e&amp;dn=The.Colbert.Report.2009.11.03.Andrew.Sullivan.PDTV.XviD-CHGRP.%5BV&amp;tr=udp%3A%2F%2Ftracker.openbittorrent.com%3A80&amp;tr=udp%3A%2F%2Fopen.demonii.com%3A1337&amp;tr=udp%3A%2F%2Ftracker.coppersurfer.tk%3A6969&amp;tr=udp%3A%2F%2Fexodus.desync.com%3A6969","seeders":2,"leechers":1,"uploader":"VTV","files":1,"time":1257385969,"description":"The Colbert Report 2009.11.03 (PDTV-CHGRP)[VTV]","torrent":{"xt":"urn:btih:1017591f4b37e627dbf12c1ffc8f2fc22454d66e","amp;dn":"The.Colbert.Report.2009.11.03.Andrew.Sullivan.PDTV.XviD-CHGRP.%5BV","amp;tr":["udp%3A%2F%2Ftracker.openbittorrent.com%3A80","udp%3A%2F%2Fopen.demonii.com%3A1337","udp%3A%2F%2Ftracker.coppersurfer.tk%3A6969","udp%3A%2F%2Fexodus.desync.com%3A6969"],"infoHash":"1017591f4b37e627dbf12c1ffc8f2fc22454d66e","infoHashBuffer":{"type":"Buffer","data":[16,23,89,31,75,55,230,39,219,241,44,31,252,143,47,194,36,84,214,110]},"announce":[],"urlList":[]}}