{"title":"Those.Who.Kill.US.S01E04.480p.HDTV.x264-mSD","uid":9910955,"size":218358931,"categoryP":"video","categoryS":"tv_shows","magnet":"?xt=urn:btih:18ce2772fb595a9a3ec72df35608b6c7d881e925&amp;dn=Those.Who.Kill.US.S01E04.480p.HDTV.x264-mSD&amp;tr=udp%3A%2F%2Ftracker.openbittorrent.com%3A80&amp;tr=udp%3A%2F%2Fopen.demonii.com%3A1337&amp;tr=udp%3A%2F%2Ftracker.coppersurfer.tk%3A6969&amp;tr=udp%3A%2F%2Fexodus.desync.com%3A6969","seeders":2,"leechers":0,"uploader":"brasse0","files":3,"time":1396896515,"description":"Those.Who.Kill.US.S01E04.480p.HDTV.x264-mSD.mkv\n\nSIZE: 218357552 bytes (208.24 MiB),\n\nDURATION: 00:42:10,\n\nAVG-BITRATE: 690 kb/s\n\nAUDIO: aac, 48000 Hz, stereo\n\nVIDEO: h264, yuv420p, 852x480, 23.98 fps(r) (eng)\n\n\n\n\nSCREENS:\n &lt;a href=&quot;\nhttp://www.vivaex.com/viewer.php?file=31915620653619069322.jpg&quot; rel=&quot;nofollow&quot; target=&quot;_NEW&quot;&gt;\nhttp://www.vivaex.com/viewer.php?file=31915620653619069322.jpg&lt;/a&gt;\n &lt;a href=&quot;\nhttp://www.vivaex.com/viewer.php?file=71340593686976169400.jpg&quot; rel=&quot;nofollow&quot; target=&quot;_NEW&quot;&gt;\nhttp://www.vivaex.com/viewer.php?file=71340593686976169400.jpg&lt;/a&gt;\n &lt;a href=&quot;\nhttp://www.vivaex.com/viewer.php?file=29796951846098253611.jpg&quot; rel=&quot;nofollow&quot; target=&quot;_NEW&quot;&gt;\nhttp://www.vivaex.com/viewer.php?file=29796951846098253611.jpg&lt;/a&gt;","torrent":{"xt":"urn:btih:18ce2772fb595a9a3ec72df35608b6c7d881e925","amp;dn":"Those.Who.Kill.US.S01E04.480p.HDTV.x264-mSD","amp;tr":["udp%3A%2F%2Ftracker.openbittorrent.com%3A80","udp%3A%2F%2Fopen.demonii.com%3A1337","udp%3A%2F%2Ftracker.coppersurfer.tk%3A6969","udp%3A%2F%2Fexodus.desync.com%3A6969"],"infoHash":"18ce2772fb595a9a3ec72df35608b6c7d881e925","infoHashBuffer":{"type":"Buffer","data":[24,206,39,114,251,89,90,154,62,199,45,243,86,8,182,199,216,129,233,37]},"announce":[],"urlList":[]}}