{"title":"Chicago PD S01E14 HDTV x264-LOL[ettv]","uid":10152877,"size":284562862,"categoryP":"video","categoryS":"tv_shows","magnet":"?xt=urn:btih:230dabd3825812b9bd7f01adff6409e8918bd962&amp;dn=Chicago+PD+S01E14+HDTV+x264-LOL%5Bettv%5D&amp;tr=udp%3A%2F%2Ftracker.openbittorrent.com%3A80&amp;tr=udp%3A%2F%2Fopen.demonii.com%3A1337&amp;tr=udp%3A%2F%2Ftracker.coppersurfer.tk%3A6969&amp;tr=udp%3A%2F%2Fexodus.desync.com%3A6969","seeders":2,"leechers":0,"uploader":"ettv","files":2,"time":1400119188,"description":"x264\nEncode Information\nResolution....: 720x404\nVideo : x264\nAudio : AAC 2ch 48khz\nFrame Rate : 23.976024 fps","torrent":{"xt":"urn:btih:230dabd3825812b9bd7f01adff6409e8918bd962","amp;dn":"Chicago+PD+S01E14+HDTV+x264-LOL%5Bettv%5D","amp;tr":["udp%3A%2F%2Ftracker.openbittorrent.com%3A80","udp%3A%2F%2Fopen.demonii.com%3A1337","udp%3A%2F%2Ftracker.coppersurfer.tk%3A6969","udp%3A%2F%2Fexodus.desync.com%3A6969"],"infoHash":"230dabd3825812b9bd7f01adff6409e8918bd962","infoHashBuffer":{"type":"Buffer","data":[35,13,171,211,130,88,18,185,189,127,1,173,255,100,9,232,145,139,217,98]},"announce":[],"urlList":[]}}