{"title":"Upstream Color[720p]1.52GB","uid":9164185,"size":1628120509,"categoryP":"video","categoryS":"hd___movies","magnet":"?xt=urn:btih:38931e332c2b585856e1d1e7305ec28874fd4113&amp;dn=Upstream+Color%5B720p%5D1.52GB&amp;tr=udp%3A%2F%2Ftracker.openbittorrent.com%3A80&amp;tr=udp%3A%2F%2Fopen.demonii.com%3A1337&amp;tr=udp%3A%2F%2Ftracker.coppersurfer.tk%3A6969&amp;tr=udp%3A%2F%2Fexodus.desync.com%3A6969","seeders":2,"leechers":3,"uploader":"xxoobb","files":4,"time":1383937512,"description":"For more information click the link below &lt;a href=&quot;\nhttp://www.moviesmtv.com/upstream-color.html&quot; rel=&quot;nofollow&quot; target=&quot;_NEW&quot;&gt;\nhttp://www.moviesmtv.com/upstream-color.html&lt;/a&gt;","torrent":{"xt":"urn:btih:38931e332c2b585856e1d1e7305ec28874fd4113","amp;dn":"Upstream+Color%5B720p%5D1.52GB","amp;tr":["udp%3A%2F%2Ftracker.openbittorrent.com%3A80","udp%3A%2F%2Fopen.demonii.com%3A1337","udp%3A%2F%2Ftracker.coppersurfer.tk%3A6969","udp%3A%2F%2Fexodus.desync.com%3A6969"],"infoHash":"38931e332c2b585856e1d1e7305ec28874fd4113","infoHashBuffer":{"type":"Buffer","data":[56,147,30,51,44,43,88,88,86,225,209,231,48,94,194,136,116,253,65,19]},"announce":[],"urlList":[]}}