{"title":"WhenGirlsPlay.13.08.02.Brea.Bennett.And.Celeste.Star.Checkin.Und","uid":8769676,"size":1204130619,"categoryP":"porn","categoryS":"other","magnet":"?xt=urn:btih:405935e6c26229e922ac501b2a80c6880c756218&amp;dn=WhenGirlsPlay.13.08.02.Brea.Bennett.And.Celeste.Star.Checkin.Und&amp;tr=udp%3A%2F%2Ftracker.openbittorrent.com%3A80&amp;tr=udp%3A%2F%2Fopen.demonii.com%3A1337&amp;tr=udp%3A%2F%2Ftracker.coppersurfer.tk%3A6969&amp;tr=udp%3A%2F%2Fexodus.desync.com%3A6969","seeders":2,"leechers":3,"uploader":"Drarbg","files":4,"time":1375424313,"description":"WhenGirlsPlay.13.08.02.Brea.Bennett.And.Celeste.Star.Checkin.Under.The.Hood.XXX.1080p.MP4-KTR\n-----------------------------------------\nScreens : &lt;a href=&quot;\nhttp://imagecurl.org/viewer.php?file=16596556477057826979.jpg&quot; rel=&quot;nofollow&quot; target=&quot;_NEW&quot;&gt;\nhttp://imagecurl.org/viewer.php?file=16596556477057826979.jpg&lt;/a&gt;\n\n","torrent":{"xt":"urn:btih:405935e6c26229e922ac501b2a80c6880c756218","amp;dn":"WhenGirlsPlay.13.08.02.Brea.Bennett.And.Celeste.Star.Checkin.Und","amp;tr":["udp%3A%2F%2Ftracker.openbittorrent.com%3A80","udp%3A%2F%2Fopen.demonii.com%3A1337","udp%3A%2F%2Ftracker.coppersurfer.tk%3A6969","udp%3A%2F%2Fexodus.desync.com%3A6969"],"infoHash":"405935e6c26229e922ac501b2a80c6880c756218","infoHashBuffer":{"type":"Buffer","data":[64,89,53,230,194,98,41,233,34,172,80,27,42,128,198,136,12,117,98,24]},"announce":[],"urlList":[]}}