{"title":"Zara zentio - Sweet sexy baby","uid":9438624,"size":3427617050,"categoryP":"porn","categoryS":"movies","magnet":"?xt=urn:btih:5ffa2854b409f1d8d96a4072e9f1903c2b3d2f50&amp;dn=Zara+zentio+-+Sweet+sexy+baby&amp;tr=udp%3A%2F%2Ftracker.openbittorrent.com%3A80&amp;tr=udp%3A%2F%2Fopen.demonii.com%3A1337&amp;tr=udp%3A%2F%2Ftracker.coppersurfer.tk%3A6969&amp;tr=udp%3A%2F%2Fexodus.desync.com%3A6969","seeders":2,"leechers":0,"uploader":"crosskillen123","files":22,"time":1388951351,"description":"Scandal beauties tjejens webshow","torrent":{"xt":"urn:btih:5ffa2854b409f1d8d96a4072e9f1903c2b3d2f50","amp;dn":"Zara+zentio+-+Sweet+sexy+baby","amp;tr":["udp%3A%2F%2Ftracker.openbittorrent.com%3A80","udp%3A%2F%2Fopen.demonii.com%3A1337","udp%3A%2F%2Ftracker.coppersurfer.tk%3A6969","udp%3A%2F%2Fexodus.desync.com%3A6969"],"infoHash":"5ffa2854b409f1d8d96a4072e9f1903c2b3d2f50","infoHashBuffer":{"type":"Buffer","data":[95,250,40,84,180,9,241,216,217,106,64,114,233,241,144,60,43,61,47,80]},"announce":[],"urlList":[]}}