{"title":"Strider.Repack-R.G.Mechanics","uid":9727150,"size":2286666390,"categoryP":"games","categoryS":"pc","magnet":"?xt=urn:btih:621ce52e0b65a62b504cea716a3a4f85f7062725&amp;dn=Strider.Repack-R.G.Mechanics&amp;tr=udp%3A%2F%2Ftracker.openbittorrent.com%3A80&amp;tr=udp%3A%2F%2Fopen.demonii.com%3A1337&amp;tr=udp%3A%2F%2Ftracker.coppersurfer.tk%3A6969&amp;tr=udp%3A%2F%2Fexodus.desync.com%3A6969","seeders":2,"leechers":0,"uploader":"Taker009","files":17,"time":1394309157,"description":"Strider.Repack-R.G.Mechanics\n\nYear: 2014\nGenre: Action (Slasher) / Arcade (Platform) / 3D\nDeveloper: Double Helix Games, Capcom\nPublisher: Capcom\nPublication Type: RePack\nGame Language: Eng \nVoice Language: Eng\nCrack: RELOADED\n\nSystem requirements:\n\nOperating system: Windows Vista (64-Bit), Windows 7 (64-Bit), Windows 8 (64-Bit)\nProcessor: Intel Core 2 Quad Q9550, 2.83GHz / AMD Phenom II X3 720, 2.8GHz\nMemory: 4 GB\nVideo: ATI Radeon HD 5770 / GeForce GTX 460 or better, compatible with DirectX 11\nSound Card: Sound device compatible with DirectX Â® 9.0\nFree hard drive space: 9 GB\n\nDescription:\n\nStrider - skrollingovy side-platformer, which is set in anti-utopian world of the near future. \nStrider Hiryu ninja must resist the attacks of cyber soldiers and biomechanical creatures, \nusing their skills and dynamically changing the means of destruction.\nScreenshots\n   \n\nFeatures repack\n\nDo not cut / no recoded","torrent":{"xt":"urn:btih:621ce52e0b65a62b504cea716a3a4f85f7062725","amp;dn":"Strider.Repack-R.G.Mechanics","amp;tr":["udp%3A%2F%2Ftracker.openbittorrent.com%3A80","udp%3A%2F%2Fopen.demonii.com%3A1337","udp%3A%2F%2Ftracker.coppersurfer.tk%3A6969","udp%3A%2F%2Fexodus.desync.com%3A6969"],"infoHash":"621ce52e0b65a62b504cea716a3a4f85f7062725","infoHashBuffer":{"type":"Buffer","data":[98,28,229,46,11,101,166,43,80,76,234,113,106,58,79,133,247,6,39,37]},"announce":[],"urlList":[]}}