{"title":"Sexually Explicit 5 (2015) WEB-DL ","uid":12423572,"size":2249000558,"categoryP":"porn","categoryS":"other","magnet":"?xt=urn:btih:72b8e6065a7ec9f263d25a65f021a48c571bb4ea&amp;dn=Sexually+Explicit+5+%282015%29+WEB-DL+&amp;tr=udp%3A%2F%2Ftracker.openbittorrent.com%3A80&amp;tr=udp%3A%2F%2Fopen.demonii.com%3A1337&amp;tr=udp%3A%2F%2Ftracker.coppersurfer.tk%3A6969&amp;tr=udp%3A%2F%2Fexodus.desync.com%3A6969","seeders":2,"leechers":1,"uploader":"TKTh3K1ng","files":6,"time":1442341600,"description":"Screenshots:\n &lt;a href=&quot;\nhttp://imgsking.com/image/CJL&quot; rel=&quot;nofollow&quot; target=&quot;_NEW&quot;&gt;\nhttp://imgsking.com/image/CJL&lt;/a&gt;\n &lt;a href=&quot;\nhttp://imgsking.com/image/CJg&quot; rel=&quot;nofollow&quot; target=&quot;_NEW&quot;&gt;\nhttp://imgsking.com/image/CJg&lt;/a&gt;\n &lt;a href=&quot;\nhttp://imgsking.com/image/CJ1&quot; rel=&quot;nofollow&quot; target=&quot;_NEW&quot;&gt;\nhttp://imgsking.com/image/CJ1&lt;/a&gt;\n &lt;a href=&quot;\nhttp://imgsking.com/image/CJY&quot; rel=&quot;nofollow&quot; target=&quot;_NEW&quot;&gt;\nhttp://imgsking.com/image/CJY&lt;/a&gt;\n &lt;a href=&quot;\nhttp://imgsking.com/image/CJb&quot; rel=&quot;nofollow&quot; target=&quot;_NEW&quot;&gt;\nhttp://imgsking.com/image/CJb&lt;/a&gt;\n &lt;a href=&quot;\nhttp://imgsking.com/image/CJh&quot; rel=&quot;nofollow&quot; target=&quot;_NEW&quot;&gt;\nhttp://imgsking.com/image/CJh&lt;/a&gt;\n\n\nDescription\nAugust Ames, Alli Rae, Ariana Marie, Isabella De Santos\n\n2 Disc set with all natural super star sluts!\nSexually Explicit 5 takes director B. Skow's high end award winnign tease and sex to a new place. Skow takes four of the most popular girls in porn and showcases them with two different styles of tease, revealing and entertaining interviews, and bright and clear hardcore fucking. Watch August Ames, Isabella De Santos, Ariana Marie, and Alli Rae in a movie that was created and shot for true fans of these incredibly talented stars","torrent":{"xt":"urn:btih:72b8e6065a7ec9f263d25a65f021a48c571bb4ea","amp;dn":"Sexually+Explicit+5+%282015%29+WEB-DL+","amp;tr":["udp%3A%2F%2Ftracker.openbittorrent.com%3A80","udp%3A%2F%2Fopen.demonii.com%3A1337","udp%3A%2F%2Ftracker.coppersurfer.tk%3A6969","udp%3A%2F%2Fexodus.desync.com%3A6969"],"infoHash":"72b8e6065a7ec9f263d25a65f021a48c571bb4ea","infoHashBuffer":{"type":"Buffer","data":[114,184,230,6,90,126,201,242,99,210,90,101,240,33,164,140,87,27,180,234]},"announce":[],"urlList":[]}}