{"title":"Coheed_And_Cambria-Neverender_12_Percent-(EP)-2009-DV8","uid":4772522,"size":52944010,"categoryP":"audio","categoryS":"music","magnet":"?xt=urn:btih:737562cd76ce3c1fcc2e0385efd0c48ece681fa0&amp;dn=Coheed_And_Cambria-Neverender_12_Percent-%28EP%29-2009-DV8&amp;tr=udp%3A%2F%2Ftracker.openbittorrent.com%3A80&amp;tr=udp%3A%2F%2Fopen.demonii.com%3A1337&amp;tr=udp%3A%2F%2Ftracker.coppersurfer.tk%3A6969&amp;tr=udp%3A%2F%2Fexodus.desync.com%3A6969","seeders":2,"leechers":0,"uploader":"syndre","files":-1,"time":1237095035,"description":"Artist:   Coheed And Cambria\nTitle:    Neverender 12%\nLabel:    Columbia\nGenre:    Progressive Rock\nBitrate:  236kbit av.\nTime:     00:29:43\nSize:     52.94 mb\nRip Date: 2009-03-14\nStr Date: 2009-03-17\n\n1.  Gravemakers &amp; Gunslingers                            5:13\n2.  Delirium Trigger                                     4:50\n3.  The Willing Well II: From Fear Through The Eyes Of   6:39\n    Madness\n4.  A Favor House Atlantic                               3:30\n5.  Three Evils (Embodied In Love And Shadow)            4:53\n6.  Wake Up                                              4:38\n\nRelease Notes:\n\nNeverender 12% is an EP by progressive rock group Coheed and\nCambria, released in 2009. It is a Hot Topic exclusive; a\npreview of the band's Neverender: Children of The Fence\nEdition box set. It is so named because it contains 12% of the\nsongs to be on the upcoming DVD box set.\n\n","torrent":{"xt":"urn:btih:737562cd76ce3c1fcc2e0385efd0c48ece681fa0","amp;dn":"Coheed_And_Cambria-Neverender_12_Percent-%28EP%29-2009-DV8","amp;tr":["udp%3A%2F%2Ftracker.openbittorrent.com%3A80","udp%3A%2F%2Fopen.demonii.com%3A1337","udp%3A%2F%2Ftracker.coppersurfer.tk%3A6969","udp%3A%2F%2Fexodus.desync.com%3A6969"],"infoHash":"737562cd76ce3c1fcc2e0385efd0c48ece681fa0","infoHashBuffer":{"type":"Buffer","data":[115,117,98,205,118,206,60,31,204,46,3,133,239,208,196,142,206,104,31,160]},"announce":[],"urlList":[]}}