{"title":"Symphony X - 1995 - The Damnation Game","uid":3918220,"size":111405318,"categoryP":"audio","categoryS":"music","magnet":"?xt=urn:btih:8a11ac2af6a799732e9a7ef955ab14611a5c9362&amp;dn=Symphony+X+-+1995+-+The+Damnation+Game&amp;tr=udp%3A%2F%2Ftracker.openbittorrent.com%3A80&amp;tr=udp%3A%2F%2Fopen.demonii.com%3A1337&amp;tr=udp%3A%2F%2Ftracker.coppersurfer.tk%3A6969&amp;tr=udp%3A%2F%2Fexodus.desync.com%3A6969","seeders":2,"leechers":0,"uploader":"-Kralder-","files":9,"time":1196618003,"description":"Symphony X - 1995 - The Damnation Game [MP3@320]","torrent":{"xt":"urn:btih:8a11ac2af6a799732e9a7ef955ab14611a5c9362","amp;dn":"Symphony+X+-+1995+-+The+Damnation+Game","amp;tr":["udp%3A%2F%2Ftracker.openbittorrent.com%3A80","udp%3A%2F%2Fopen.demonii.com%3A1337","udp%3A%2F%2Ftracker.coppersurfer.tk%3A6969","udp%3A%2F%2Fexodus.desync.com%3A6969"],"infoHash":"8a11ac2af6a799732e9a7ef955ab14611a5c9362","infoHashBuffer":{"type":"Buffer","data":[138,17,172,42,246,167,153,115,46,154,126,249,85,171,20,97,26,92,147,98]},"announce":[],"urlList":[]}}