{"title":"Some more rare astrology,palmistry and occult books","uid":4954023,"size":296319140,"categoryP":"other","categoryS":"e_books","magnet":"?xt=urn:btih:95e4250472760cda40fd8e5d3172fb5b0b522acb&amp;dn=Some+more+rare+astrology%2Cpalmistry+and+occult+books&amp;tr=udp%3A%2F%2Ftracker.openbittorrent.com%3A80&amp;tr=udp%3A%2F%2Fopen.demonii.com%3A1337&amp;tr=udp%3A%2F%2Ftracker.coppersurfer.tk%3A6969&amp;tr=udp%3A%2F%2Fexodus.desync.com%3A6969","seeders":2,"leechers":0,"uploader":"sharath_1861","files":7,"time":1245020022,"description":"1)jataka tatva by V.SUBRAHMANYA SHASTRI printed in 1941\n\njataka tatva (eng trans: &quot;the philosophy of horoscope&quot;) this is one of the classics in vedic astrology by the veteran \ntranslator.irony is translator wasn't a professional astrologer nor a student of it but translation is so excellent that \neven a expert can't be so good!\n\n2)MOHINI VIDYA SADHANA AND SIDDHI BY A.L.BHAGWAT PRINTED IN 1975\n\nONE OF THE BEST, RAREST,GREAT (WHATEVER U MAY CALL IT)BOOK I'VE COME ACROSS.BESIDES ITS SIMPLE EXPLAINATION IT ALSO GIVES A SERIES OF EXERCISE IN GAZING AND WHAT NOT!.\nI STRONGLY RECOMMEND THAT ONE SHOULD ATLEAST TRY SOME EXERCISES AND B SURE THAT U WILL COME ACROSS THAT XTRA SENSE OR 6TH\nSENSE WHICH PPL REFER TO.\nI'LL UPLOAD EXERCISE CHARTS DESIGNED BY ME BASED ON THE DETAILS PROVIDED IN THE BOOK\nENJOY!\n\n3)Science of palmistry by M.A.DEVACHARYA date unknown but not that old\n\none of the good palmistry books based on research\n\n4)TETRABIBLIOS BY PTOLEMY PRINTED IN 1882\n\nthis is something like an aphorisms i feel try it out and say if it works perfectly!\n\n5)choice aphorisms from 7 segments of cardan edited by william lilly in 1675\n\naphorisms related to nativity,accident and general queries answered according to astrological principles\n\n6)christian astrology by william lilly\n\nof course this is like a classic in western astrology\n\n\ni've many more books to share but only when u ppl comment whether it's bad r good i don mind but i need some feedback\ndon't just restrain urself from commenting on my upload and don't just limit it to &quot;thanks&quot; or &quot; good upload&quot;\n\nbandwidth slower so pls bear with me and don't forget to seed after u download","torrent":{"xt":"urn:btih:95e4250472760cda40fd8e5d3172fb5b0b522acb","amp;dn":"Some+more+rare+astrology%2Cpalmistry+and+occult+books","amp;tr":["udp%3A%2F%2Ftracker.openbittorrent.com%3A80","udp%3A%2F%2Fopen.demonii.com%3A1337","udp%3A%2F%2Ftracker.coppersurfer.tk%3A6969","udp%3A%2F%2Fexodus.desync.com%3A6969"],"infoHash":"95e4250472760cda40fd8e5d3172fb5b0b522acb","infoHashBuffer":{"type":"Buffer","data":[149,228,37,4,114,118,12,218,64,253,142,93,49,114,251,91,11,82,42,203]},"announce":[],"urlList":[]}}