{"title":"Twisted Wheel - Twisted Wheel (2009)","uid":6912921,"size":85535937,"categoryP":"audio","categoryS":"other","magnet":"?xt=urn:btih:970bb2b0f635838458ba1445cd3b4fb31f04a149&amp;dn=Twisted+Wheel+-+Twisted+Wheel+%282009%29&amp;tr=udp%3A%2F%2Ftracker.openbittorrent.com%3A80&amp;tr=udp%3A%2F%2Fopen.demonii.com%3A1337&amp;tr=udp%3A%2F%2Ftracker.coppersurfer.tk%3A6969&amp;tr=udp%3A%2F%2Fexodus.desync.com%3A6969","seeders":2,"leechers":1,"uploader":"woollytorrent","files":11,"time":1324910392,"description":"Twisted Wheel - Twisted Wheel (2009) \n\n320 kbps","torrent":{"xt":"urn:btih:970bb2b0f635838458ba1445cd3b4fb31f04a149","amp;dn":"Twisted+Wheel+-+Twisted+Wheel+%282009%29","amp;tr":["udp%3A%2F%2Ftracker.openbittorrent.com%3A80","udp%3A%2F%2Fopen.demonii.com%3A1337","udp%3A%2F%2Ftracker.coppersurfer.tk%3A6969","udp%3A%2F%2Fexodus.desync.com%3A6969"],"infoHash":"970bb2b0f635838458ba1445cd3b4fb31f04a149","infoHashBuffer":{"type":"Buffer","data":[151,11,178,176,246,53,131,132,88,186,20,69,205,59,79,179,31,4,161,73]},"announce":[],"urlList":[]}}