{"title":"RealExGirlFriends - Cookies And Cock - Alexis Adams [1080p].mp4","uid":11653008,"size":1301714039,"categoryP":"porn","categoryS":"hd___movies","magnet":"?xt=urn:btih:b19f8b715697b7da11f3fc5535f17dc15ecaf6ef&amp;dn=RealExGirlFriends+-+Cookies+And+Cock+-+Alexis+Adams+%5B1080p%5D.mp4&amp;tr=udp%3A%2F%2Ftracker.openbittorrent.com%3A80&amp;tr=udp%3A%2F%2Fopen.demonii.com%3A1337&amp;tr=udp%3A%2F%2Ftracker.coppersurfer.tk%3A6969&amp;tr=udp%3A%2F%2Fexodus.desync.com%3A6969","seeders":2,"leechers":9,"uploader":"C3Porno","files":-1,"time":1417894276,"description":"RealExGirlFriends - Cookies And Cock - Alexis Adams [1080p].mp4\n\n2014, All Sex, Straight, Hardcore, Oral, HD, XXX, Adult\n\n1920 x 1080\n\n00:20:47\n\n1.21 GB\n\nScreens\n &lt;a href=&quot;\nhttp://imgcentral.com/viewer.php?file=80792682233839295369.jpg&quot; rel=&quot;nofollow&quot; target=&quot;_NEW&quot;&gt;\nhttp://imgcentral.com/viewer.php?file=80792682233839295369.jpg&lt;/a&gt;\n &lt;a href=&quot;\nhttp://imgcentral.com/viewer.php?file=53184068160994613343.jpg&quot; rel=&quot;nofollow&quot; target=&quot;_NEW&quot;&gt;\nhttp://imgcentral.com/viewer.php?file=53184068160994613343.jpg&lt;/a&gt;\n &lt;a href=&quot;\nhttp://imgcentral.com/viewer.php?file=83102821110792831119.jpg&quot; rel=&quot;nofollow&quot; target=&quot;_NEW&quot;&gt;\nhttp://imgcentral.com/viewer.php?file=83102821110792831119.jpg&lt;/a&gt;\n &lt;a href=&quot;\nhttp://imgcentral.com/viewer.php?file=14379770815573602238.jpg&quot; rel=&quot;nofollow&quot; target=&quot;_NEW&quot;&gt;\nhttp://imgcentral.com/viewer.php?file=14379770815573602238.jpg&lt;/a&gt;\n &lt;a href=&quot;\nhttp://imgcentral.com/viewer.php?file=81928398259490213940.jpg&quot; rel=&quot;nofollow&quot; target=&quot;_NEW&quot;&gt;\nhttp://imgcentral.com/viewer.php?file=81928398259490213940.jpg&lt;/a&gt;","torrent":{"xt":"urn:btih:b19f8b715697b7da11f3fc5535f17dc15ecaf6ef","amp;dn":"RealExGirlFriends+-+Cookies+And+Cock+-+Alexis+Adams+%5B1080p%5D.mp4","amp;tr":["udp%3A%2F%2Ftracker.openbittorrent.com%3A80","udp%3A%2F%2Fopen.demonii.com%3A1337","udp%3A%2F%2Ftracker.coppersurfer.tk%3A6969","udp%3A%2F%2Fexodus.desync.com%3A6969"],"infoHash":"b19f8b715697b7da11f3fc5535f17dc15ecaf6ef","infoHashBuffer":{"type":"Buffer","data":[177,159,139,113,86,151,183,218,17,243,252,85,53,241,125,193,94,202,246,239]},"announce":[],"urlList":[]}}