{"title":"Awkward.S03E11.1080p.WEB-DL.AAC2.0.H.264-KiNGS [PublicHD]","uid":9091218,"size":754172373,"categoryP":"video","categoryS":"hd___tv_shows","magnet":"?xt=urn:btih:b588d7582d6e874d7ff01cd4e3200d8bbd750de8&amp;dn=Awkward.S03E11.1080p.WEB-DL.AAC2.0.H.264-KiNGS+%5BPublicHD%5D&amp;tr=udp%3A%2F%2Ftracker.openbittorrent.com%3A80&amp;tr=udp%3A%2F%2Fopen.demonii.com%3A1337&amp;tr=udp%3A%2F%2Ftracker.coppersurfer.tk%3A6969&amp;tr=udp%3A%2F%2Fexodus.desync.com%3A6969","seeders":2,"leechers":3,"uploader":"DibyaTPB","files":3,"time":1382600434,"description":"\n                PublicHD - High-Definition Bittorrent Community\n      \n                               \n              ----------------------------------------------------\n\nAwkward.S03E11.1080p.WEB-DL.AAC2.0.H.264-KiNGS [PublicHD]\n \nLength..............: 19mn 29s\nVideo...............: H264 @ 5158Kbps (1916x1076)\nFPS.................: 23.976 FPS\nAudio...............: AAC","torrent":{"xt":"urn:btih:b588d7582d6e874d7ff01cd4e3200d8bbd750de8","amp;dn":"Awkward.S03E11.1080p.WEB-DL.AAC2.0.H.264-KiNGS+%5BPublicHD%5D","amp;tr":["udp%3A%2F%2Ftracker.openbittorrent.com%3A80","udp%3A%2F%2Fopen.demonii.com%3A1337","udp%3A%2F%2Ftracker.coppersurfer.tk%3A6969","udp%3A%2F%2Fexodus.desync.com%3A6969"],"infoHash":"b588d7582d6e874d7ff01cd4e3200d8bbd750de8","infoHashBuffer":{"type":"Buffer","data":[181,136,215,88,45,110,135,77,127,240,28,212,227,32,13,139,189,117,13,232]},"announce":[],"urlList":[]}}