{"title":"Now Thats What I Call Music 1991","uid":6046894,"size":204098453,"categoryP":"audio","categoryS":"music","magnet":"?xt=urn:btih:b9982040c658d4ac2b7e1a58bac2ee0e4e44acb2&amp;dn=Now+Thats+What+I+Call+Music+1991&amp;tr=udp%3A%2F%2Ftracker.openbittorrent.com%3A80&amp;tr=udp%3A%2F%2Fopen.demonii.com%3A1337&amp;tr=udp%3A%2F%2Ftracker.coppersurfer.tk%3A6969&amp;tr=udp%3A%2F%2Fexodus.desync.com%3A6969","seeders":2,"leechers":0,"uploader":"fanclubt","files":38,"time":1292546794,"description":"Now Thats What I Call Music.1991\n\nCD 1\n\n01 The Show Must Go On - Queen\n02 The Whole of the Moon - The Waterboys\n03 Sit Down - James\n04 Sailing on the Seven Seas - Orchestral Manoeuvres in the Dark\n05 Where the Streets Have No Name (I Can't Take My Eyes off You) - Pet Shop Boys\n06 Love to Hate You - Erasure\n07 I'm Too Sexy - Right Said Fred \n08 Let's Talk About Sex - Salt-N-Pepa\n09 Now That We Found Love - Heavy D &amp; the Boyz\n10 Set Adrift on Memory Bliss - P.M. Dawn\n11 Summertime - DJ Jazzy Jeff &amp; the Fresh Prince\n12 You Got the Love - Candi Stanton/The Source\n13 Gypsy Woman (La da Dee) - Crystal Waters\n14 Always There - Incognito/Jocelyn Brown\n15 Touch Me (All Night Long) -Cathy Dennis\n16 Rhythm Is a Mystery - K-Klass\n17 Apparently Nothin' - Young Disciples\n18 There's Nothing Like This - Omar\n\nCD 2\n\n01 The Fly - U2\n02 There's No Other Way - Blur\n03 The Size of a Cow - The Wonder Stuff\n04 Word of Mouth - Mike + the Mechanics\n05 Driven by You - Brian May\n06 Joyride - Roxette\n07 Wind of Change - Scorpions\n08 Fall at Your Feet - Crowded House\n09 Saltwater - Julian Lennon\n10 More Than Words - Extreme\n11 Get Here - Oleta Adams\n12 Sadeness, Pt. 1 - Enigma\n13 It's Too Late - Dina Carroll/Quartz\n14 Baby Baby - Amy Grant\n15 Thinking About Your Love - Kenny Thomas\n16 Any Dream Will Do - Jason Donovan\n17 Always Look on the Bright Side of Life - Monty Python\n18 Dizzy - Monty Python","torrent":{"xt":"urn:btih:b9982040c658d4ac2b7e1a58bac2ee0e4e44acb2","amp;dn":"Now+Thats+What+I+Call+Music+1991","amp;tr":["udp%3A%2F%2Ftracker.openbittorrent.com%3A80","udp%3A%2F%2Fopen.demonii.com%3A1337","udp%3A%2F%2Ftracker.coppersurfer.tk%3A6969","udp%3A%2F%2Fexodus.desync.com%3A6969"],"infoHash":"b9982040c658d4ac2b7e1a58bac2ee0e4e44acb2","infoHashBuffer":{"type":"Buffer","data":[185,152,32,64,198,88,212,172,43,126,26,88,186,194,238,14,78,68,172,178]},"announce":[],"urlList":[]}}