{"title":"Dont.Give.Up.On.Us.2006.DVDRip.XviD-A-R","uid":3467153,"size":731863935,"categoryP":"video","categoryS":"movies","magnet":"?xt=urn:btih:d5dbeb6eb4a459a4398b7b20d86198d4f55cc5e1&amp;dn=Dont.Give.Up.On.Us.2006.DVDRip.XviD-A-R&amp;tr=udp%3A%2F%2Ftracker.openbittorrent.com%3A80&amp;tr=udp%3A%2F%2Fopen.demonii.com%3A1337&amp;tr=udp%3A%2F%2Ftracker.coppersurfer.tk%3A6969&amp;tr=udp%3A%2F%2Fexodus.desync.com%3A6969","seeders":2,"leechers":0,"uploader":"d34d85","files":3,"time":1144302890,"description":"Title: Dont Give Up On Us\n\n[img]http://i5.photobucket.com/albums/y162/d34d/stdguou.jpg[/img]\n\nDescription: Abby is an advertising executive who goes on vacation to thenorth, in Baguio and Sagada. There, she meets Vince, an aspiring rocksinger. They immediately get on each other&amp;#039;s nerves, but given theirdifferences, is love workable between them?\n\nDirected By.....: Joyce Bernal\nCOUNTRY......: Philippines\nLanguage......: Tagalog\n\nCast Members:\n\nJudy Ann Santos\tas Abby\nPiolo Pascual as Vince\nTommy Abuel\t\t\nMarco Alcaraz\t\t\nMarjorie Barretto\t\t\nJ.C. Cuadrado\t\t\nCheska Diaz\t\t\nChesca Garcia\nHilda Koronel\t\t\nRio Locsin\t\t\nJohn Wayne Sace\n   and much more...","torrent":{"xt":"urn:btih:d5dbeb6eb4a459a4398b7b20d86198d4f55cc5e1","amp;dn":"Dont.Give.Up.On.Us.2006.DVDRip.XviD-A-R","amp;tr":["udp%3A%2F%2Ftracker.openbittorrent.com%3A80","udp%3A%2F%2Fopen.demonii.com%3A1337","udp%3A%2F%2Ftracker.coppersurfer.tk%3A6969","udp%3A%2F%2Fexodus.desync.com%3A6969"],"infoHash":"d5dbeb6eb4a459a4398b7b20d86198d4f55cc5e1","infoHashBuffer":{"type":"Buffer","data":[213,219,235,110,180,164,89,164,57,139,123,32,216,97,152,212,245,92,197,225]},"announce":[],"urlList":[]}}