{"title":"Don't Stop Believin - Journey - Escape [1981] [FLAC] [24 bit 96","uid":10770579,"size":42903122,"categoryP":"audio","categoryS":"flac","magnet":"?xt=urn:btih:f6eabca2f2b16f98f4eddebc7cd3e7365dc0f795&amp;dn=Don%27t+Stop+Believin+-+Journey+-+Escape+%5B1981%5D+%5BFLAC%5D+%5B24+bit+96+&amp;tr=udp%3A%2F%2Ftracker.openbittorrent.com%3A80&amp;tr=udp%3A%2F%2Fopen.demonii.com%3A1337&amp;tr=udp%3A%2F%2Ftracker.coppersurfer.tk%3A6969&amp;tr=udp%3A%2F%2Fexodus.desync.com%3A6969","seeders":2,"leechers":0,"uploader":"S_K_G","files":1,"time":1408071582,"description":"Unadulterated vinyl rip.\n\n1 (one) TRACK (not the entire album!!!)\n\nDon't Stop Believin - Journey from the album ESCAPE 4:11\n\nRipped from album: Escape\n96 khz, 24 bit\n\n \nThis is probably one of the best rips i've done, to date, very good quality vinyl from start to finish, very pleased with what I came up with!\n\n\n\nPlease comment if you have any tips or comments \n \nThanks\n\nS_K_G \t \t\t","torrent":{"xt":"urn:btih:f6eabca2f2b16f98f4eddebc7cd3e7365dc0f795","amp;dn":"Don%27t+Stop+Believin+-+Journey+-+Escape+%5B1981%5D+%5BFLAC%5D+%5B24+bit+96+","amp;tr":["udp%3A%2F%2Ftracker.openbittorrent.com%3A80","udp%3A%2F%2Fopen.demonii.com%3A1337","udp%3A%2F%2Ftracker.coppersurfer.tk%3A6969","udp%3A%2F%2Fexodus.desync.com%3A6969"],"infoHash":"f6eabca2f2b16f98f4eddebc7cd3e7365dc0f795","infoHashBuffer":{"type":"Buffer","data":[246,234,188,162,242,177,111,152,244,237,222,188,124,211,231,54,93,192,247,149]},"announce":[],"urlList":[]}}