{"title":"[Twistys] Sunny Leone (Sunny With A Chance Of Orgasm / 06.24.201","uid":8610725,"size":1039450279,"categoryP":"porn","categoryS":"hd___movies","magnet":"?xt=urn:btih:f74aeb2bf51b639861021e6dc59aa96dddd61e75&amp;dn=%5BTwistys%5D+Sunny+Leone+%28Sunny+With+A+Chance+Of+Orgasm+%2F+06.24.201&amp;tr=udp%3A%2F%2Ftracker.openbittorrent.com%3A80&amp;tr=udp%3A%2F%2Fopen.demonii.com%3A1337&amp;tr=udp%3A%2F%2Ftracker.coppersurfer.tk%3A6969&amp;tr=udp%3A%2F%2Fexodus.desync.com%3A6969","seeders":2,"leechers":1,"uploader":"chkm8te","files":1,"time":1372126329,"description":"[Twistys] Sunny Leone (Sunny With A Chance Of Orgasm / 06.24.2013)\nres:720p\n\nScreens: &lt;a href=&quot;\nhttp://xxxhost.me/viewer.php?file=59yr71vzb5z9zuadwxhj.jpg&quot; rel=&quot;nofollow&quot; target=&quot;_NEW&quot;&gt;\nhttp://xxxhost.me/viewer.php?file=59yr71vzb5z9zuadwxhj.jpg&lt;/a&gt;\n &lt;a href=&quot;\nhttp://xxxhost.me/viewer.php?file=tf5ol3x9d5hj06bty395.jpg&quot; rel=&quot;nofollow&quot; target=&quot;_NEW&quot;&gt;\nhttp://xxxhost.me/viewer.php?file=tf5ol3x9d5hj06bty395.jpg&lt;/a&gt;","torrent":{"xt":"urn:btih:f74aeb2bf51b639861021e6dc59aa96dddd61e75","amp;dn":"%5BTwistys%5D+Sunny+Leone+%28Sunny+With+A+Chance+Of+Orgasm+%2F+06.24.201","amp;tr":["udp%3A%2F%2Ftracker.openbittorrent.com%3A80","udp%3A%2F%2Fopen.demonii.com%3A1337","udp%3A%2F%2Ftracker.coppersurfer.tk%3A6969","udp%3A%2F%2Fexodus.desync.com%3A6969"],"infoHash":"f74aeb2bf51b639861021e6dc59aa96dddd61e75","infoHashBuffer":{"type":"Buffer","data":[247,74,235,43,245,27,99,152,97,2,30,109,197,154,169,109,221,214,30,117]},"announce":[],"urlList":[]}}